calc_rs-0.2.0.dist-info/METADATA
calc_rs-0.2.0.dist-info/WHEEL
calc_rs-0.2.0.dist-info/license_files/LICENSE
calculators/__init__.py
calculators/calculators.pypy37-pp73-s390x-linux-gnu.so
calc_rs-0.2.0.dist-info/RECORD
